pprintpp.py
pprintpp/__init__.py
pprintpp/safesort.py
pprintpp-0.3.0.dist-info/DESCRIPTION.rst
pprintpp-0.3.0.dist-info/entry_points.txt
pprintpp-0.3.0.dist-info/METADATA
pprintpp-0.3.0.dist-info/metadata.json
pprintpp-0.3.0.dist-info/RECORD
pprintpp-0.3.0.dist-info/top_level.txt
pprintpp-0.3.0.dist-info/WHEEL
