Metadata-Version: 1.1
Name: pprintpp
Version: 0.3.0
Summary: A drop-in replacement for pprint that's actually pretty
Home-page: https://github.com/wolever/pprintpp
Author: David Wolever
Author-email: david@wolever.net
License: BSD
Platform: UNKNOWN
Classifier: Development Status :: 3 - Alpha
Classifier: Environment :: Console
Classifier: Intended Audience :: Developers
Classifier: License :: OSI Approved :: BSD License
Classifier: Natural Language :: English
Classifier: Operating System :: OS Independent
Classifier: Programming Language :: Python
Classifier: Programming Language :: Python :: 2
Classifier: Programming Language :: Python :: 3
Classifier: Topic :: Software Development
Classifier: Topic :: Utilities
